{
    "iDontFollowBack": [
        {
            "username": "joechoii",
            "full_name": "Joe Choi"
        },
        {
            "username": "veronicacwong",
            "full_name": "ronnie wong"
        },
        {
            "username": "benlai._",
            "full_name": "Ben Lai"
        },
        {
            "username": "helen.zhu.5855",
            "full_name": "Helen Zhu"
        },
        {
            "username": "darpitydarp",
            "full_name": "Matt Liu"
        },
        {
            "username": "hiro.yosh",
            "full_name": "Hiro Yoshizaki"
        },
        {
            "username": "tchoe711",
            "full_name": "Tenzin Choerab"
        },
        {
            "username": "ianna.1010",
            "full_name": "ianna"
        },
        {
            "username": "kyle_pagui",
            "full_name": ""
        },
        {
            "username": "isaaclcaasi",
            "full_name": "Isaac Lyu"
        },
        {
            "username": "dillonguyen",
            "full_name": "Dillon Nguyen"
        },
        {
            "username": "dxxanny",
            "full_name": "Danny"
        },
        {
            "username": "choijohn02",
            "full_name": "John Choi"
        },
        {
            "username": "ryanshunke",
            "full_name": "Ryan Shunke He"
        },
        {
            "username": "kt_kory",
            "full_name": "Kory T"
        },
        {
            "username": "lovekoala.88000",
            "full_name": "Bao"
        },
        {
            "username": "saumithg22",
            "full_name": "Saumith Gundapuneedi"
        },
        {
            "username": "de.stineee",
            "full_name": "destinee 🤍"
        },
        {
            "username": "ethanvnguyen",
            "full_name": "Ethan Nguyen"
        },
        {
            "username": "jalen.mcb",
            "full_name": "Jalen Cauley"
        },
        {
            "username": "jaycrickcrack",
            "full_name": "Jason Lei"
        },
        {
            "username": "casperhclin",
            "full_name": "Casper"
        },
        {
            "username": "slirvivi",
            "full_name": "V"
        },
        {
            "username": "kietnguyen0116",
            "full_name": "Kiet Nguyen"
        },
        {
            "username": "chase_1230",
            "full_name": "Chase Tuck"
        },
        {
            "username": "mariana.rocioo",
            "full_name": "mari🪴"
        },
        {
            "username": "anthonypertico",
            "full_name": "Anthony Perticone"
        },
        {
            "username": "jewelry_by_colette",
            "full_name": "Colette"
        },
        {
            "username": "adnan.rahimzai",
            "full_name": "Adnan"
        },
        {
            "username": "calebthemayer",
            "full_name": "Caleb Mayer"
        },
        {
            "username": "chantilly.hstea",
            "full_name": ""
        },
        {
            "username": "ronitbh1",
            "full_name": "Ronit Bhansali"
        },
        {
            "username": "vcu.2025",
            "full_name": "Virginia Commonwealth C/O 2025"
        },
        {
            "username": "k80lew1s",
            "full_name": "kaitlin"
        },
        {
            "username": "csaatvcu",
            "full_name": "CSA@VCU"
        },
        {
            "username": "glyzelleelaine",
            "full_name": "not glizzy."
        },
        {
            "username": "paulcoww",
            "full_name": "paul"
        },
        {
            "username": "rudra.s_",
            "full_name": "rudra sheth"
        },
        {
            "username": "kevin_being_kevin",
            "full_name": "Kevin Nguyen"
        },
        {
            "username": "alexanderbekele",
            "full_name": "Alexander Berhanu Bekele"
        },
        {
            "username": "zeroxxanh",
            "full_name": "Anh Ha"
        },
        {
            "username": "michaeld3768",
            "full_name": "Michael Doan"
        },
        {
            "username": "don.nguyen23",
            "full_name": "Don Nguyen"
        },
        {
            "username": "raychulbro",
            "full_name": "Mala fama, buena vida"
        },
        {
            "username": "_enm6",
            "full_name": ""
        },
        {
            "username": "jenny.n.tran",
            "full_name": "Jenny Tran"
        },
        {
            "username": "timotheytrann",
            "full_name": "Tim :)"
        },
        {
            "username": "sluio",
            "full_name": "Sam Baugher"
        },
        {
            "username": "what.the_fung",
            "full_name": "Jonathan Fung"
        },
        {
            "username": "sarah_campbell_",
            "full_name": "sarah"
        },
        {
            "username": "lxshala",
            "full_name": "LaShala ;)"
        },
        {
            "username": "mensvballclubvcu",
            "full_name": "VCU Men’s Volleyball Club"
        },
        {
            "username": "vsavcu",
            "full_name": "VSA at VCU"
        },
        {
            "username": "sriyabasavaraju",
            "full_name": "Sriya Basavaraju"
        },
        {
            "username": "rushils.photo",
            "full_name": "Rushil Suresh"
        },
        {
            "username": "alexxpadillaa",
            "full_name": "Alex Padilla 🌞🍄🌿🌈"
        },
        {
            "username": "becky.woolf",
            "full_name": "Becky Woolf"
        },
        {
            "username": "akhilkamalesh",
            "full_name": "Akhil Kamalesh"
        },
        {
            "username": "vcu_eng",
            "full_name": "VCU College Of Engineering"
        },
        {
            "username": "jocelyn.lii",
            "full_name": ""
        },
        {
            "username": "jla_han",
            "full_name": "julia han"
        },
        {
            "username": "pooja_and_rushil",
            "full_name": "Rushil Suresh & Pooja Loga"
        },
        {
            "username": "rushil_s.20",
            "full_name": "Rushil Suresh"
        },
        {
            "username": "avanmiller15",
            "full_name": "Ava Miller"
        },
        {
            "username": "ayy_ham",
            "full_name": "ayham أيهم"
        },
        {
            "username": "andrew.e.griner",
            "full_name": "Andrew Griner"
        },
        {
            "username": "aneesdrivingschool",
            "full_name": "Anees Rehman"
        },
        {
            "username": "chs_memes.exe",
            "full_name": "CHS Official Meme Account"
        },
        {
            "username": "maynaire_w",
            "full_name": "Maynaire Wang"
        },
        {
            "username": "sophie_jjjjj",
            "full_name": "Soph"
        },
        {
            "username": "chs.floor.tiles",
            "full_name": "Chantilly Floor Tiles"
        },
        {
            "username": "chs_windows",
            "full_name": "the windows of Chantilly HS"
        },
        {
            "username": "zachsrelics",
            "full_name": "Zach Markers 🖍"
        },
        {
            "username": "chantillycultureclub",
            "full_name": "CHS Culture Club"
        },
        {
            "username": "brian_bippert",
            "full_name": "Brian Bippert"
        },
        {
            "username": "parker_agan",
            "full_name": "Parker Agan"
        },
        {
            "username": "daniel_fucking_sucks",
            "full_name": "Daniel Zhang"
        },
        {
            "username": "dumbpl1ng",
            "full_name": ""
        },
        {
            "username": "clen_hogan",
            "full_name": "Glenn Hogan"
        },
        {
            "username": "shreyaatripathy",
            "full_name": "Shreya Tripathy"
        },
        {
            "username": "vanessaloraine322",
            "full_name": "Vanessa Scola"
        },
        {
            "username": "tillycompliments",
            "full_name": "Chantilly Compliments"
        },
        {
            "username": "priya.rachakonda",
            "full_name": "Priya Rachakonda"
        },
        {
            "username": "_tim.ph",
            "full_name": "tim"
        },
        {
            "username": "shozzz7",
            "full_name": "Shoma Zafar"
        },
        {
            "username": "banana.yacht",
            "full_name": "da boat"
        },
        {
            "username": "m.a.x_james_",
            "full_name": "Maximus James"
        },
        {
            "username": "tdonipati",
            "full_name": "Tarun Donipati"
        },
        {
            "username": "alyssaluskk",
            "full_name": "Alyssa"
        },
        {
            "username": "jessicaa.liii",
            "full_name": "jessica li"
        },
        {
            "username": "kendra.bush2",
            "full_name": "kendra bush"
        },
        {
            "username": "colejencks",
            "full_name": "Cole Jencks"
        },
        {
            "username": "srirambasavaraju",
            "full_name": "Sriram Basavaraju"
        },
        {
            "username": "_elizabethwu_",
            "full_name": "elizabeth wu"
        },
        {
            "username": "neighboraaron",
            "full_name": "Aaron Lin"
        },
        {
            "username": "tfitzhugh_",
            "full_name": "Tommy Fitzhugh"
        },
        {
            "username": "ptslammer4",
            "full_name": "Sam Brunner"
        },
        {
            "username": "chsxctrackmemes",
            "full_name": "CHS XC / Track Memes 🏃🏼‍♂️🏃‍♀️"
        },
        {
            "username": "sarahiahmed",
            "full_name": "Sarah"
        },
        {
            "username": "chantilly.secret.group",
            "full_name": "Chantilly HS Tea"
        },
        {
            "username": "nandiniramkumar",
            "full_name": "Nandini Ramkumar"
        },
        {
            "username": "jaya.sreee",
            "full_name": "Jayasree Allam"
        },
        {
            "username": "kerul.mathur",
            "full_name": "Kerul Mathur"
        },
        {
            "username": "s.soyy",
            "full_name": "soy wong"
        },
        {
            "username": "caileezeraat",
            "full_name": "c :)"
        },
        {
            "username": "shikhakin",
            "full_name": "👁 shikha 👁"
        },
        {
            "username": "r00h4n_",
            "full_name": "rohan palle"
        },
        {
            "username": "madeleinelebeau",
            "full_name": "Madeleine LeBeau"
        },
        {
            "username": "julia_gusmati",
            "full_name": "julia giovanna gusmati"
        },
        {
            "username": "share_it_tilly_",
            "full_name": "Chantilly"
        },
        {
            "username": "fishyvcnugget3k00",
            "full_name": "Victor Phan"
        },
        {
            "username": "chantilly.jsa",
            "full_name": "Jewish Student Association"
        },
        {
            "username": "berthold__hannah",
            "full_name": "Hannah"
        },
        {
            "username": "smithuin_",
            "full_name": "Mathuin Smith"
        },
        {
            "username": "namwoooooo",
            "full_name": "namwoo"
        },
        {
            "username": "703bape",
            "full_name": "been in the field"
        },
        {
            "username": "kyles.project.dump",
            "full_name": "Kyle"
        },
        {
            "username": "dylanjamesisme",
            "full_name": "Dylan James"
        },
        {
            "username": "_wonthanhsoup",
            "full_name": "Th@nh"
        },
        {
            "username": "sasha.cello",
            "full_name": "Alexandra (Sasha) Lukashuk"
        },
        {
            "username": "kevan15535",
            "full_name": "Kevin Phan"
        },
        {
            "username": "cassidykortum14",
            "full_name": "Cassidy Kortum"
        },
        {
            "username": "stevoon.naguwin",
            "full_name": "Measlystevie"
        },
        {
            "username": "k3eth",
            "full_name": "Keith Orr"
        },
        {
            "username": "minht.ha",
            "full_name": "minhtrung ha"
        },
        {
            "username": "notiepos",
            "full_name": "Justin Ngô"
        },
        {
            "username": "notused1221",
            "full_name": ""
        },
        {
            "username": "mr.man_21",
            "full_name": "My Name Quan"
        },
        {
            "username": "pranavrathore00",
            "full_name": "Pranav Rathore"
        },
        {
            "username": "sydney.tucker",
            "full_name": "sydney"
        },
        {
            "username": "jason_kimm23",
            "full_name": "Jason Kim"
        },
        {
            "username": "_.lily.nguyen._",
            "full_name": ""
        },
        {
            "username": "palash.shah",
            "full_name": "Palash Shah"
        },
        {
            "username": "thomas21tran",
            "full_name": "Thomas Tran"
        },
        {
            "username": "mary.orlando26",
            "full_name": "Mary  Orlando"
        },
        {
            "username": "dante.liftsss",
            "full_name": "D@v°n+€"
        },
        {
            "username": "colton_applegate",
            "full_name": "Colton Applegate"
        },
        {
            "username": "jkinb1gd0ng",
            "full_name": "Drizzy Jkin"
        },
        {
            "username": "_jadehoward",
            "full_name": "jade"
        },
        {
            "username": "claire_and_julia",
            "full_name": "Claire and Julia"
        },
        {
            "username": "samsaham21",
            "full_name": "Sam Fitzhugh"
        },
        {
            "username": "kyle_beene",
            "full_name": "Kyle Beene"
        },
        {
            "username": "atom_gains",
            "full_name": "SuavePapi 🌊"
        },
        {
            "username": "alexfontinhaspam",
            "full_name": "private spam shit"
        },
        {
            "username": "akheeeeeel",
            "full_name": "Akheeeeeel"
        },
        {
            "username": "kaavimusic_",
            "full_name": "Kaavya Parikh"
        },
        {
            "username": "adam.jaynes21",
            "full_name": "Adam Jaynes"
        },
        {
            "username": "noahdvdbrown",
            "full_name": "Noah Brown"
        },
        {
            "username": "theofficialkingdante",
            "full_name": "D@v¤Ωt€"
        },
        {
            "username": "sakky1012",
            "full_name": "Saketh Addagarla"
        },
        {
            "username": "see.thesy",
            "full_name": "Phat Loaf"
        },
        {
            "username": "sat_on_a_wik_fanpage",
            "full_name": "Satwik Fanpage"
        },
        {
            "username": "leo_clougherty",
            "full_name": "Leo Clougherty"
        },
        {
            "username": "cho.g123",
            "full_name": "Gregory Cho"
        },
        {
            "username": "cameronhadley2",
            "full_name": "Cameron Hadley"
        },
        {
            "username": "justin_h_park",
            "full_name": "Justin Park"
        },
        {
            "username": "hunch0a",
            "full_name": "Zoobi"
        },
        {
            "username": "justin__brady",
            "full_name": "Justin Brady"
        },
        {
            "username": "sachin.manivannan",
            "full_name": "Sachin Manivannan"
        },
        {
            "username": "lime.not.lemon",
            "full_name": "Liem Nguyen"
        },
        {
            "username": "lambertspamzzz",
            "full_name": "Lambert.spamzzz"
        },
        {
            "username": "aganta2",
            "full_name": "Akshay Ganta"
        },
        {
            "username": "akshayganta7",
            "full_name": "Akshay Ganta"
        },
        {
            "username": "swindeller",
            "full_name": "Ryan S"
        },
        {
            "username": "drpepperluvr_",
            "full_name": "d ~<3"
        },
        {
            "username": "krishiganee",
            "full_name": "Krishigan Yuvaraj"
        },
        {
            "username": "saffasaturdays",
            "full_name": ""
        },
        {
            "username": "ryandinnh",
            "full_name": "ryan dinh"
        },
        {
            "username": "chungghlee",
            "full_name": "Chung Hyun Lee"
        },
        {
            "username": "jpham_26",
            "full_name": "Justin Pham"
        },
        {
            "username": "cadenglodde_too",
            "full_name": "Spam"
        },
        {
            "username": "tt11hdvn",
            "full_name": "Thang Tien 11"
        },
        {
            "username": "thisistunam",
            "full_name": "Тu-Nam Nguyen"
        },
        {
            "username": "bornimusic",
            "full_name": "Born I / Ofosu Jones-Quartey"
        },
        {
            "username": "sonakshirout",
            "full_name": ""
        },
        {
            "username": "tobeyphan",
            "full_name": "Tobey Phan"
        },
        {
            "username": "vijayrudraraju",
            "full_name": ""
        },
        {
            "username": "srimanth.t",
            "full_name": "Srimanth"
        },
        {
            "username": "nelscwilliams",
            "full_name": "Nels Williams"
        },
        {
            "username": "varshak.11",
            "full_name": "varsha"
        },
        {
            "username": "arjun_bhatia1234",
            "full_name": ""
        },
        {
            "username": "zoe_varacalli",
            "full_name": "Zoe"
        },
        {
            "username": "lbsssneakers",
            "full_name": "LBSS Sneakers"
        },
        {
            "username": "connor0mcintire",
            "full_name": ""
        },
        {
            "username": "annabelhapp",
            "full_name": "annabel!!!!!!!"
        },
        {
            "username": "arnav_jadhav",
            "full_name": "Arnav Jadhav"
        },
        {
            "username": "bschuman2002",
            "full_name": "Ben Schuman"
        },
        {
            "username": "tiffanyfungus",
            "full_name": "tiffany fung"
        },
        {
            "username": "ariii.angeles",
            "full_name": "αяιєℓℓє αиgєℓєѕ"
        },
        {
            "username": "orangeboy_73",
            "full_name": "Patrick Mountcastle"
        },
        {
            "username": "arii.angeles",
            "full_name": "αяιєℓℓє αиgєℓєѕ"
        },
        {
            "username": "vivekiyer.20",
            "full_name": "Vivek"
        },
        {
            "username": "dylannguyen15",
            "full_name": "Dylan Nguyen"
        },
        {
            "username": "moomoomoo_mee",
            "full_name": ""
        },
        {
            "username": "katielatham.3",
            "full_name": "Katie Latham"
        },
        {
            "username": "bella.allison",
            "full_name": "b e l l a :) 🇵🇭"
        },
        {
            "username": "eliseemomo",
            "full_name": "elise mccue 🪩"
        },
        {
            "username": "tmmontoya",
            "full_name": "Tristan Montoya"
        },
        {
            "username": "xrlee024",
            "full_name": ""
        },
        {
            "username": "jasman1080p",
            "full_name": "Jason Hagerman Jr."
        },
        {
            "username": "jackconne11",
            "full_name": "Jack Connell"
        },
        {
            "username": "skyauraman",
            "full_name": ""
        },
        {
            "username": "malspabatsanta",
            "full_name": "Malcolm Neifeld"
        },
        {
            "username": "the_hannah.s",
            "full_name": "Hannah&Hannah"
        },
        {
            "username": "megatron.xox",
            "full_name": "Dear Meghan"
        },
        {
            "username": "kenneth6271",
            "full_name": "Kenneth"
        },
        {
            "username": "unhappy.cat",
            "full_name": "account dead? or just lurking? fuck you!"
        },
        {
            "username": "floating__fairy",
            "full_name": "Mary Katherine Orlando"
        },
        {
            "username": "millers.members.only",
            "full_name": "New to Bea, love her already"
        },
        {
            "username": "hannahpeacelove",
            "full_name": "👋"
        },
        {
            "username": "heygeoffrey",
            "full_name": "Geoffrey Nguyen"
        },
        {
            "username": "hannah_rose_me",
            "full_name": "Follow main @xhannah.wagnerx"
        },
        {
            "username": "climate._.change",
            "full_name": "POLLUTION IS BAD"
        },
        {
            "username": "katy.is.a.unicorn_",
            "full_name": "Katy Cat😻"
        },
        {
            "username": "megan__fanpage",
            "full_name": "Keaton💋"
        },
        {
            "username": "hannah__wagner",
            "full_name": "нαииαн"
        },
        {
            "username": "serena_gulajan",
            "full_name": ""
        },
        {
            "username": "brandonnewguyin",
            "full_name": "brandon"
        }
    ]
}
